perforated_backpropagation-1.0.0.dist-info/top_level.txt
perforated_backpropagation-1.0.0.dist-info/WHEEL
perforated_backpropagation-1.0.0.dist-info/RECORD
perforated_backpropagation-1.0.0.dist-info/METADATA
PAI/pb_neuron_layer_tracker.cpython-39-x86_64-linux-gnu.so
PAI/blockwisePB.cpython-39-x86_64-linux-gnu.so
PAI/globalsFile.cpython-39-x86_64-linux-gnu.so
PAI/cleanLoad.cpython-39-x86_64-linux-gnu.so
PAI/pb_utils.cpython-39-x86_64-linux-gnu.so
PAI/pb_models.cpython-39-x86_64-linux-gnu.so
PAI/pb_layer.cpython-39-x86_64-linux-gnu.so
PAI/__init__.cpython-39-x86_64-linux-gnu.so
PAI/check_license.cpython-39-x86_64-linux-gnu.so
